{
  "type": "FeatureCollection",
  "features": [
    {
      "type": "Feature",
      "geometry": {
        "type": "Polygon",
        "coordinates": [
          [
            [
              -0.55628437483,
              53.22875016262
            ],
            [
              -0.55625720889,
              53.22876634859
            ],
            [
              -0.5562493299,
              53.22876163206
            ],
            [
              -0.55623541594,
              53.22875310216
            ],
            [
              -0.55626257331,
              53.22873699569
            ],
            [
              -0.55628437483,
              53.22875016262
            ]
          ]
        ]
      },
      "properties": {
        "building": "CSB",
        "geometry_type": "Polygon",
        "level": "1",
        "node_type": "block",
        "NAV_FEATURE": "yes"
      }
    },
    {
      "type": "Feature",
      "geometry": {
        "type": "Polygon",
        "coordinates": [
          [
            [
              -0.55630636328,
              53.22881122778
            ],
            [
              -0.55627648727,
              53.22879319268
            ],
            [
              -0.55630020806,
              53.22877904309
            ],
            [
              -0.55633021527,
              53.22879705622
            ],
            [
              -0.55630636328,
              53.22881122778
            ]
          ]
        ]
      },
      "properties": {
        "building": "CSB",
        "connected_nodes": "l_csb0_053, c_csb1_001, l_csb2_053",
        "geometry_type": "Polygon",
        "id": "l_csb1_053",
        "level": "1",
        "name": "CSB1053 (Lift)",
        "node_type": "Lift",
        "NAV_FEATURE": "yes"
      }
    },
    {
      "type": "Feature",
      "geometry": {
        "type": "Polygon",
        "coordinates": [
          [
            [
              -0.5562939,
              53.2288424
            ],
            [
              -0.55627406015,
              53.22883042055
            ],
            [
              -0.55622661495,
              53.22880177274
            ],
            [
              -0.55620993496,
              53.22881150685
            ],
            [
              -0.55617037238,
              53.22878772351
            ],
            [
              -0.55620599546,
              53.22876649912
            ],
            [
              -0.556223346,
              53.22877698588
            ],
            [
              -0.5562493299,
              53.22876163206
            ],
            [
              -0.55623541594,
              53.22875310216
            ],
            [
              -0.55626257331,
              53.22873699569
            ],
            [
              -0.55628437483,
              53.22875016262
            ],
            [
              -0.55631622968,
              53.22876945227
            ],
            [
              -0.55636626972,
              53.22879962262
            ],
            [
              -0.5564646,
              53.2287415
            ],
            [
              -0.5562838,
              53.2286319
            ],
            [
              -0.5559983,
              53.2288007
            ],
            [
              -0.5561791,
              53.2289103
            ],
            [
              -0.5562939,
              53.2288424
            ]
          ]
        ]
      },
      "properties": {
        "building": "CSB",
        "connected_nodes": "c_csb1_003, c_csb1_005",
        "geometry_type": "Polygon",
        "id": "r_csb1_001",
        "level": "1",
        "name": "CSB1001 (School of Maths & Physics / College of Science PGR)",
        "node_type": "other",
        "NAV_FEATURE": "yes"
      }
    },
    {
      "type": "Feature",
      "geometry": {
        "type": "Polygon",
        "coordinates": [
          [
            [
              -0.55631622968,
              53.22876945227
            ],
            [
              -0.55630020806,
              53.22877904309
            ],
            [
              -0.55633021527,
              53.22879705622
            ],
            [
              -0.55630636328,
              53.22881122778
            ],
            [
              -0.55627406015,
              53.22883042055
            ],
            [
              -0.5562939,
              53.2288424
            ],
            [
              -0.55636626972,
              53.22879962262
            ],
            [
              -0.55631622968,
              53.22876945227
            ]
          ]
        ]
      },
      "properties": {
        "building": "CSB",
        "connected_nodes": "s_csb0_060, c_csb1_005, c_csb1_001, s_csb2_051",
        "geometry_type": "Polygon",
        "id": "s_csb1_051",
        "level": "1",
        "name": "CSB1051 (Stairs)",
        "node_type": "Stairs",
        "NAV_FEATURE": "yes"
      }
    },
    {
      "type": "Feature",
      "geometry": {
        "type": "Polygon",
        "coordinates": [
          [
            [
              -0.55622661495,
              53.22880177274
            ],
            [
              -0.55624530659,
              53.22879048318
            ],
            [
              -0.556223346,
              53.22877698588
            ],
            [
              -0.55620599546,
              53.22876649912
            ],
            [
              -0.55617037238,
              53.22878772351
            ],
            [
              -0.55620993496,
              53.22881150685
            ],
            [
              -0.55622661495,
              53.22880177274
            ]
          ]
        ]
      },
      "properties": {
        "building": "CSB",
        "connected_nodes": "c_csb1_003",
        "geometry_type": "Polygon",
        "id": "wcf_csb1_054",
        "level": "1",
        "name": "CSB1054 (WC Female)",
        "node_type": "wcf",
        "NAV_FEATURE": "yes"
      }
    },
    {
      "type": "Feature",
      "geometry": {
        "type": "Polygon",
        "coordinates": [
          [
            [
              -0.55625720889,
              53.22876634859
            ],
            [
              -0.55627154191,
              53.22877505408
            ],
            [
              -0.55624530659,
              53.22879048318
            ],
            [
              -0.556223346,
              53.22877698588
            ],
            [
              -0.5562493299,
              53.22876163206
            ],
            [
              -0.55625720889,
              53.22876634859
            ]
          ]
        ]
      },
      "properties": {
        "building": "CSB",
        "connected_nodes": "c_csb1_004",
        "geometry_type": "Polygon",
        "id": "wcm_csb1_055",
        "level": "1",
        "name": "CSB1055 (WC Male)",
        "node_type": "wcm",
        "NAV_FEATURE": "yes"
      }
    }
  ]
}