{
  "type": "FeatureCollection",
  "features": [
    {
      "type": "Feature",
      "geometry": {
        "type": "Polygon",
        "coordinates": [
          [
            [
              -0.5492507988,
              53.22811287799
            ],
            [
              -0.54921499945,
              53.22810245735
            ],
            [
              -0.54924247978,
              53.22806935014
            ],
            [
              -0.54927776576,
              53.22807953571
            ],
            [
              -0.54926686929,
              53.22809288271
            ],
            [
              -0.5492507988,
              53.22811287799
            ]
          ]
        ]
      },
      "properties": {
        "building": "JLC",
        "geometry_type": "Polygon",
        "level": "1",
        "node_type": "Block",
        "NAV_FEATURE": "yes"
      }
    },
    {
      "type": "Feature",
      "geometry": {
        "type": "Polygon",
        "coordinates": [
          [
            [
              -0.54983997765,
              53.22822058087
            ],
            [
              -0.54986118809,
              53.22822670363
            ],
            [
              -0.54990347492,
              53.22817441976
            ],
            [
              -0.54988247812,
              53.22816834832
            ],
            [
              -0.54983997765,
              53.22822058087
            ]
          ]
        ]
      },
      "properties": {
        "building": "JLC",
        "geometry_type": "Polygon",
        "level": "1",
        "node_type": "Block",
        "NAV_FEATURE": "yes"
      }
    },
    {
      "type": "Feature",
      "geometry": {
        "type": "Polygon",
        "coordinates": [
          [
            [
              -0.54936063011,
              53.22816974308
            ],
            [
              -0.5494058412,
              53.22811400705
            ],
            [
              -0.54938488644,
              53.22810793568
            ],
            [
              -0.5493396346,
              53.22816359277
            ],
            [
              -0.54936063011,
              53.22816974308
            ]
          ]
        ]
      },
      "properties": {
        "building": "JLC",
        "geometry_type": "Polygon",
        "level": "1",
        "node_type": "Block",
        "NAV_FEATURE": "yes"
      }
    },
    {
      "type": "Feature",
      "geometry": {
        "type": "Polygon",
        "coordinates": [
          [
            [
              -0.54941926409,
              53.22809755199
            ],
            [
              -0.54939846512,
              53.22809145265
            ],
            [
              -0.54944112914,
              53.22803929404
            ],
            [
              -0.54946191613,
              53.228045265
            ],
            [
              -0.54941926409,
              53.22809755199
            ]
          ]
        ]
      },
      "properties": {
        "building": "JLC",
        "geometry_type": "Polygon",
        "level": "1",
        "node_type": "Block",
        "NAV_FEATURE": "yes"
      }
    },
    {
      "type": "Feature",
      "geometry": {
        "type": "Polygon",
        "coordinates": [
          [
            [
              -0.54980240833,
              53.22829883874
            ],
            [
              -0.54984773518,
              53.22824311137
            ],
            [
              -0.54982674215,
              53.22823684711
            ],
            [
              -0.54978127453,
              53.22829272615
            ],
            [
              -0.54980240833,
              53.22829883874
            ]
          ]
        ]
      },
      "properties": {
        "building": "JLC",
        "geometry_type": "Polygon",
        "level": "1",
        "node_type": "Block",
        "NAV_FEATURE": "yes"
      }
    },
    {
      "type": "Feature",
      "geometry": {
        "type": "Polygon",
        "coordinates": [
          [
            [
              -0.54930904231,
              53.2280433954
            ],
            [
              -0.54927280561,
              53.22803271645
            ],
            [
              -0.54930142497,
              53.22799843189
            ],
            [
              -0.54933702582,
              53.22800868618
            ],
            [
              -0.54932202221,
              53.22802730176
            ],
            [
              -0.54930904231,
              53.2280433954
            ]
          ]
        ]
      },
      "properties": {
        "building": "JLC",
        "geometry_type": "Polygon",
        "level": "1",
        "node_type": "Block",
        "NAV_FEATURE": "yes"
      }
    },
    {
      "type": "Feature",
      "geometry": {
        "type": "Polygon",
        "coordinates": [
          [
            [
              -0.54990615704,
              53.22826358338
            ],
            [
              -0.54992174738,
              53.22824426543
            ],
            [
              -0.54988486701,
              53.22823342731
            ],
            [
              -0.54984245466,
              53.22828606248
            ],
            [
              -0.54987933495,
              53.22829690053
            ],
            [
              -0.54990615704,
              53.22826358338
            ]
          ]
        ]
      },
      "properties": {
        "building": "JLC",
        "geometry_type": "Polygon",
        "level": "1",
        "node_type": "Block",
        "NAV_FEATURE": "yes"
      }
    },
    {
      "type": "Feature",
      "geometry": {
        "type": "Polygon",
        "coordinates": [
          [
            [
              -0.54926686929,
              53.22809288271
            ],
            [
              -0.54927776576,
              53.22807953571
            ],
            [
              -0.54930812185,
              53.22808842646
            ],
            [
              -0.54935965695,
              53.22810352016
            ],
            [
              -0.54934867666,
              53.22811681697
            ],
            [
              -0.54926686929,
              53.22809288271
            ]
          ]
        ]
      },
      "properties": {
        "building": "JLC",
        "geometry_type": "Polygon",
        "level": "1",
        "node_type": "Block",
        "NAV_FEATURE": "yes"
      }
    },
    {
      "type": "Feature",
      "geometry": {
        "type": "Polygon",
        "coordinates": [
          [
            [
              -0.54933224838,
              53.22813658671
            ],
            [
              -0.54934867666,
              53.22811681697
            ],
            [
              -0.54926686929,
              53.22809288271
            ],
            [
              -0.5492507988,
              53.22811287799
            ],
            [
              -0.54933224838,
              53.22813658671
            ]
          ]
        ]
      },
      "properties": {
        "building": "JLC",
        "geometry_type": "Polygon",
        "level": "1",
        "node_type": "Block",
        "NAV_FEATURE": "yes"
      }
    },
    {
      "type": "Feature",
      "geometry": {
        "type": "Polygon",
        "coordinates": [
          [
            [
              -0.54996198052,
              53.22820623164
            ],
            [
              -0.54992191502,
              53.22819438998
            ],
            [
              -0.54990431302,
              53.22821646765
            ],
            [
              -0.54994412706,
              53.22822795807
            ],
            [
              -0.54996198052,
              53.22820623164
            ]
          ]
        ]
      },
      "properties": {
        "building": "JLC",
        "connected_nodes": "c_jlc1_010, l_jlc0_171,l_jlc2_171",
        "geometry_type": "Polygon",
        "id": "l_jlc1_171",
        "level": "1",
        "name": "JLC1171 (Lift)",
        "node_type": "Lift",
        "NAV_FEATURE": "yes"
      }
    },
    {
      "type": "Feature",
      "geometry": {
        "type": "Polygon",
        "coordinates": [
          [
            [
              -0.54973422784,
              53.22809666042
            ],
            [
              -0.54964483528,
              53.22807020742
            ],
            [
              -0.54966829387,
              53.22804118975
            ],
            [
              -0.54975833788,
              53.22806754382
            ],
            [
              -0.54973422784,
              53.22809666042
            ]
          ]
        ]
      },
      "properties": {
        "building": "JLC",
        "connected_nodes": "c_jlc1_007",
        "geometry_type": "Polygon",
        "id": "r_jlc1_105",
        "level": "1",
        "name": "JLC1105 (Office)",
        "node_type": "other",
        "NAV_FEATURE": "yes"
      }
    },
    {
      "type": "Feature",
      "geometry": {
        "type": "Polygon",
        "coordinates": [
          [
            [
              -0.54994636633,
              53.22815850989
            ],
            [
              -0.54992711188,
              53.22818199642
            ],
            [
              -0.54998562125,
              53.22819899856
            ],
            [
              -0.55002227497,
              53.2282096497
            ],
            [
              -0.55004211159,
              53.22821541399
            ],
            [
              -0.55005095629,
              53.22820420494
            ],
            [
              -0.55008468282,
              53.22816321483
            ],
            [
              -0.54996970905,
              53.2281293159
            ],
            [
              -0.54994636633,
              53.22815850989
            ]
          ]
        ]
      },
      "properties": {
        "building": "JLC",
        "connected_nodes": "c_jlc1_008",
        "geometry_type": "Polygon",
        "id": "r_jlc1_107",
        "level": "1",
        "name": "JLC1107 (Office)",
        "node_type": "Room",
        "NAV_FEATURE": "yes"
      }
    },
    {
      "type": "Feature",
      "geometry": {
        "type": "Polygon",
        "coordinates": [
          [
            [
              -0.5494058412,
              53.22811400705
            ],
            [
              -0.54941926409,
              53.22809755199
            ],
            [
              -0.54946191613,
              53.228045265
            ],
            [
              -0.54965704682,
              53.22810231588
            ],
            [
              -0.5495424771,
              53.2282429222
            ],
            [
              -0.54947348328,
              53.22822304082
            ],
            [
              -0.54948639141,
              53.22820658292
            ],
            [
              -0.54936063011,
              53.22816974308
            ],
            [
              -0.5494058412,
              53.22811400705
            ]
          ]
        ]
      },
      "properties": {
        "building": "JLC",
        "connected_nodes": "c_jlc1_003",
        "geometry_type": "Polygon",
        "id": "r_jlc1_103",
        "level": "1",
        "name": "JLC1103 (Generic Lab 2)",
        "node_type": "Room",
        "NAV_FEATURE": "yes"
      }
    },
    {
      "type": "Feature",
      "geometry": {
        "type": "Polygon",
        "coordinates": [
          [
            [
              -0.54919067837,
              53.22813212119
            ],
            [
              -0.54921499945,
              53.22810245735
            ],
            [
              -0.5492507988,
              53.22811287799
            ],
            [
              -0.54933224838,
              53.22813658671
            ],
            [
              -0.54931618412,
              53.22815672331
            ],
            [
              -0.5492911,
              53.2281885
            ],
            [
              -0.54917302071,
              53.22815369435
            ],
            [
              -0.54919067837,
              53.22813212119
            ]
          ]
        ]
      },
      "properties": {
        "building": "JLC",
        "connected_nodes": "c_jlc1_004",
        "geometry_type": "Polygon",
        "id": "r_jlc1_101",
        "level": "1",
        "name": "JLC1101 (Instrument Lab)",
        "node_type": "Room",
        "NAV_FEATURE": "yes"
      }
    },
    {
      "type": "Feature",
      "geometry": {
        "type": "Polygon",
        "coordinates": [
          [
            [
              -0.54933702582,
              53.22800868618
            ],
            [
              -0.54930142497,
              53.22799843189
            ],
            [
              -0.54934429095,
              53.22794619222
            ],
            [
              -0.54945685568,
              53.22797959646
            ],
            [
              -0.54943337638,
              53.22800850389
            ],
            [
              -0.54941472606,
              53.22803136607
            ],
            [
              -0.54937558257,
              53.22801992577
            ],
            [
              -0.54933702582,
              53.22800868618
            ]
          ]
        ]
      },
      "properties": {
        "building": "JLC",
        "connected_nodes": "c_jlc1_006",
        "geometry_type": "Polygon",
        "id": "r_jlc1_104",
        "level": "1",
        "name": "JLC1104 (Office)",
        "node_type": "Room",
        "NAV_FEATURE": "yes"
      }
    },
    {
      "type": "Feature",
      "geometry": {
        "type": "Polygon",
        "coordinates": [
          [
            [
              -0.54996491418,
              53.2282807939
            ],
            [
              -0.54993884655,
              53.22831245527
            ],
            [
              -0.54995745437,
              53.22831777397
            ],
            [
              -0.54994856212,
              53.22832909294
            ],
            [
              -0.54991501257,
              53.22837032751
            ],
            [
              -0.54980050153,
              53.22833711235
            ],
            [
              -0.54982617208,
              53.228305712
            ],
            [
              -0.54984245466,
              53.22828606248
            ],
            [
              -0.54987933495,
              53.22829690053
            ],
            [
              -0.54990615704,
              53.22826358338
            ],
            [
              -0.54992694416,
              53.2282697049
            ],
            [
              -0.54996491418,
              53.2282807939
            ]
          ]
        ]
      },
      "properties": {
        "building": "JLC",
        "connected_nodes": "c_jlc1_015",
        "geometry_type": "Polygon",
        "id": "r_jlc1_109",
        "level": "1",
        "name": "JLC1109 (Pharmacy Formulation Lab)",
        "node_type": "Room",
        "NAV_FEATURE": "yes"
      }
    },
    {
      "type": "Feature",
      "geometry": {
        "type": "Polygon",
        "coordinates": [
          [
            [
              -0.5495424771,
              53.2282429222
            ],
            [
              -0.54963994788,
              53.22827100954
            ],
            [
              -0.54965285601,
              53.22825525413
            ],
            [
              -0.54978127453,
              53.22829272615
            ],
            [
              -0.54982674215,
              53.22823684711
            ],
            [
              -0.54983997765,
              53.22822058087
            ],
            [
              -0.54988247812,
              53.22816834832
            ],
            [
              -0.54965704682,
              53.22810231588
            ],
            [
              -0.5495424771,
              53.2282429222
            ]
          ]
        ]
      },
      "properties": {
        "building": "JLC",
        "connected_nodes": "c_jlc1_014",
        "geometry_type": "Polygon",
        "id": "r_jlc1_106",
        "level": "1",
        "name": "JLC1106 (Generic Lab 1)",
        "node_type": "Room",
        "NAV_FEATURE": "yes"
      }
    },
    {
      "type": "Feature",
      "geometry": {
        "type": "Polygon",
        "coordinates": [
          [
            [
              -0.54927776576,
              53.22807953571
            ],
            [
              -0.54924247978,
              53.22806935014
            ],
            [
              -0.54927280561,
              53.22803271645
            ],
            [
              -0.54930904231,
              53.2280433954
            ],
            [
              -0.54933803173,
              53.22805193858
            ],
            [
              -0.54930812185,
              53.22808842646
            ],
            [
              -0.54927776576,
              53.22807953571
            ]
          ]
        ]
      },
      "properties": {
        "building": "JLC",
        "connected_nodes": "c_jlc1_001, s_jlc0_155, s_jlc2_157",
        "geometry_type": "Polygon",
        "id": "s_jlc1_155",
        "level": "1",
        "name": "JLC1155 (Stairs East)",
        "node_type": "Stairs",
        "NAV_FEATURE": "yes"
      }
    },
    {
      "type": "Feature",
      "geometry": {
        "type": "Polygon",
        "coordinates": [
          [
            [
              -0.54999525667,
              53.22824296084
            ],
            [
              -0.5500293711,
              53.22825284566
            ],
            [
              -0.55003607654,
              53.22825826467
            ],
            [
              -0.55004009994,
              53.22826508872
            ],
            [
              -0.5500394293,
              53.22827191267
            ],
            [
              -0.55003607662,
              53.22827923848
            ],
            [
              -0.55002761082,
              53.22828500872
            ],
            [
              -0.55001663061,
              53.22828927377
            ],
            [
              -0.55000565023,
              53.22829027725
            ],
            [
              -0.54999517294,
              53.22828967518
            ],
            [
              -0.54996491418,
              53.2282807939
            ],
            [
              -0.54992694416,
              53.2282697049
            ],
            [
              -0.54995742062,
              53.22823185875
            ],
            [
              -0.54999525667,
              53.22824296084
            ]
          ]
        ]
      },
      "properties": {
        "building": "JLC",
        "connected_nodes": "c_jlc1_012, s_jlc2_173, s_jlc0_174",
        "geometry_type": "Polygon",
        "id": "s_jlc1_172",
        "level": "1",
        "name": "JLC1172 (Stairs West)",
        "node_type": "Stairs",
        "NAV_FEATURE": "yes"
      }
    },
    {
      "type": "Feature",
      "geometry": {
        "type": "Polygon",
        "coordinates": [
          [
            [
              -0.54935932168,
              53.22805816044
            ],
            [
              -0.54938488644,
              53.22806566183
            ],
            [
              -0.54940156647,
              53.22804526502
            ],
            [
              -0.54937600167,
              53.22803788905
            ],
            [
              -0.54935932168,
              53.22805816044
            ]
          ]
        ]
      },
      "properties": {
        "building": "JLC",
        "connected_nodes": "c_jlc1_005",
        "geometry_type": "Polygon",
        "id": "wcd_jlc1_159",
        "level": "1",
        "name": "Disabled & Gender Neutral Toilet",
        "node_type": "wcd",
        "NAV_FEATURE": "yes"
      }
    },
    {
      "type": "Feature",
      "geometry": {
        "type": "Polygon",
        "coordinates": [
          [
            [
              -0.55000774571,
              53.22822755666
            ],
            [
              -0.54999525667,
              53.22824296084
            ],
            [
              -0.54995742062,
              53.22823185875
            ],
            [
              -0.54994412706,
              53.22822795807
            ],
            [
              -0.54996198052,
              53.22820623164
            ],
            [
              -0.54997638055,
              53.22821051686
            ],
            [
              -0.54997128443,
              53.22821686906
            ],
            [
              -0.55000774571,
              53.22822755666
            ]
          ]
        ]
      },
      "properties": {
        "building": "JLC",
        "connected_nodes": "c_jlc1_010",
        "geometry_type": "Polygon",
        "id": "wcf_jlc1_168",
        "level": "1",
        "name": "JLC1168 (Female WC)",
        "node_type": "wcf",
        "NAV_FEATURE": "yes"
      }
    },
    {
      "type": "Feature",
      "geometry": {
        "type": "Polygon",
        "coordinates": [
          [
            [
              -0.54933803173,
              53.22805193858
            ],
            [
              -0.54935932168,
              53.22805816044
            ],
            [
              -0.54937600167,
              53.22803788905
            ],
            [
              -0.54936393172,
              53.22803437668
            ],
            [
              -0.54936049514,
              53.22803849117
            ],
            [
              -0.54932202221,
              53.22802730176
            ],
            [
              -0.54930904231,
              53.2280433954
            ],
            [
              -0.54933803173,
              53.22805193858
            ]
          ]
        ]
      },
      "properties": {
        "building": "JLC",
        "connected_nodes": "c_jlc1_005",
        "geometry_type": "Polygon",
        "id": "wcf_jlc1_162",
        "level": "1",
        "name": "JLC1162 (Female WC)",
        "node_type": "wcf",
        "NAV_FEATURE": "yes"
      }
    },
    {
      "type": "Feature",
      "geometry": {
        "type": "Polygon",
        "coordinates": [
          [
            [
              -0.54932202221,
              53.22802730176
            ],
            [
              -0.54933702582,
              53.22800868618
            ],
            [
              -0.54937558257,
              53.22801992577
            ],
            [
              -0.54936393172,
              53.22803437668
            ],
            [
              -0.54936049514,
              53.22803849117
            ],
            [
              -0.54932202221,
              53.22802730176
            ]
          ]
        ]
      },
      "properties": {
        "building": "JLC",
        "connected_nodes": "c_jlc1_005",
        "geometry_type": "Polygon",
        "id": "wcm_jlc1_163",
        "level": "1",
        "name": "JLC1163 (Male WC)",
        "node_type": "wcm",
        "NAV_FEATURE": "yes"
      }
    },
    {
      "type": "Feature",
      "geometry": {
        "type": "Polygon",
        "coordinates": [
          [
            [
              -0.55002227497,
              53.2282096497
            ],
            [
              -0.55000774571,
              53.22822755666
            ],
            [
              -0.54997128443,
              53.22821686906
            ],
            [
              -0.54997638055,
              53.22821051686
            ],
            [
              -0.54998562125,
              53.22819899856
            ],
            [
              -0.55002227497,
              53.2282096497
            ]
          ]
        ]
      },
      "properties": {
        "building": "JLC",
        "connected_nodes": "c_jlc1_010",
        "geometry_type": "Polygon",
        "id": "wcm_jlc1_167",
        "level": "1",
        "name": "JLC1167 (Male WC)",
        "node_type": "wcm",
        "NAV_FEATURE": "yes"
      }
    }
  ]
}